MANIFEST.in
README.md
README.rst
build_topic_model_browser.py
infer_topics.py
setup.cfg
setup.py
browser/static/css/jquery.dataTables.min.css
browser/static/css/style.css
browser/static/fonts/opensans-bold.eot
browser/static/fonts/opensans-bold.ttf
browser/static/fonts/opensans-bold.woff
browser/static/fonts/opensans.eot
browser/static/fonts/opensans.ttf
browser/static/fonts/opensans.woff
browser/static/js/d3-tip.js
browser/static/js/d3.min.js
browser/static/js/jquery-1.12.0.min.js
browser/static/js/jquery.dataTables.min.js
browser/templates/document.html
browser/templates/index.html
browser/templates/topic.html
browser/templates/topic_cloud.html
browser/templates/vocabulary.html
browser/templates/word.html
input/egc_lemmatized.csv
tom_lib/__init__.py
tom_lib/stats.py
tom_lib/utils.py
tom_lib.egg-info/PKG-INFO
tom_lib.egg-info/SOURCES.txt
tom_lib.egg-info/dependency_links.txt
tom_lib.egg-info/requires.txt
tom_lib.egg-info/top_level.txt
tom_lib/nlp/__init__.py
tom_lib/nlp/topic_model.py
tom_lib/structure/__init__.py
tom_lib/structure/author_topic_graph.py
tom_lib/structure/corpus.py
tom_lib/visualization/__init__.py
tom_lib/visualization/visualization.py