Metadata-Version: 1.1
Name: tom-lib
Version: 0.2.1
Summary: A library for topic modeling and browsing
Home-page: http://mediamining.univ-lyon2.fr/people/guille/tom.php
Author: Adrien Guille, Pavel Soriano
Author-email: adrien.guille@univ-lyon2.fr
License: MIT
Download-URL: http://pypi.python.org/packages/source/t/tom_lib/tom_lib-0.2.1.tar.gz
Platform: UNKNOWN
Classifier: Programming Language :: Python
Classifier: Development Status :: 4 - Beta
Classifier: Intended Audience :: Science/Research
Classifier: Operating System :: OS Independent
Classifier: Programming Language :: Python :: 2.7
Classifier: Topic :: Scientific/Engineering
Classifier: Topic :: Text Processing
